plaid2/__init__.py
plaid2/async_client.py
plaid2/authenticator.py
plaid2/client.py
plaid2/logger.py
plaid2/model/__init__.py
plaid2/model/access_token.py
plaid2/model/access_token_nullable.py
plaid2/model/account_access.py
plaid2/model/account_assets.py
plaid2/model/account_balance.py
plaid2/model/account_base.py
plaid2/model/account_filter.py
plaid2/model/account_filter_subtypes.py
plaid2/model/account_filters_response.py
plaid2/model/account_identity.py
plaid2/model/account_ids_with_updated_identity.py
plaid2/model/account_product_access.py
plaid2/model/account_product_access_nullable.py
plaid2/model/account_selection_cardinality.py
plaid2/model/account_subtype.py
plaid2/model/account_subtypes.py
plaid2/model/account_type.py
plaid2/model/accounts_balance_get_request.py
plaid2/model/accounts_balance_get_request_options.py
plaid2/model/accounts_get_request.py
plaid2/model/accounts_get_request_options.py
plaid2/model/accounts_get_response.py
plaid2/model/ach_class.py
plaid2/model/address.py
plaid2/model/address_data.py
plaid2/model/address_data_nullable.py
plaid2/model/address_nullable.py
plaid2/model/address_purpose_label.py
plaid2/model/api_client_id.py
plaid2/model/api_secret.py
plaid2/model/application.py
plaid2/model/application_get_request.py
plaid2/model/application_get_response.py
plaid2/model/application_id.py
plaid2/model/apr.py
plaid2/model/asset_report.py
plaid2/model/asset_report_audit_copy_create_request.py
plaid2/model/asset_report_audit_copy_create_response.py
plaid2/model/asset_report_audit_copy_get_request.py
plaid2/model/asset_report_audit_copy_remove_request.py
plaid2/model/asset_report_audit_copy_remove_response.py
plaid2/model/asset_report_create_request.py
plaid2/model/asset_report_create_request_options.py
plaid2/model/asset_report_create_response.py
plaid2/model/asset_report_filter_request.py
plaid2/model/asset_report_filter_response.py
plaid2/model/asset_report_get_request.py
plaid2/model/asset_report_get_response.py
plaid2-0.2.0.dist-info/LICENSE
plaid2-0.2.0.dist-info/WHEEL
plaid2-0.2.0.dist-info/METADATA
plaid2-0.2.0.dist-info/RECORD
