Metadata-Version: 2.1
Name: plaid2
Version: 0.2.0
Summary: Plaid client, generated from the OpenAPI spec.
Requires-Python: >=3.7
Requires-Dist: pydantic>=1.10.2
Requires-Dist: aiohttp>=3.8.3
Requires-Dist: requests>=2.28.1
Requires-Dist: urllib3>=1.26.12
